WinUtils.cp37-win32.pyd
WinUtils-1.1.2.data/data/LICENSE
WinUtils-1.1.2.dist-info/METADATA
WinUtils-1.1.2.dist-info/RECORD
WinUtils-1.1.2.dist-info/WHEEL
WinUtils-1.1.2.dist-info/top_level.txt
