Metadata-Version: 2.1
Name: WinUtils
Version: 1.1.2
Summary: A module to provide simplified system calls on Windows
Home-page: https://github.com/Simon3335/WinUtils
Author: Simon
License: MIT
Platform: UNKNOWN
Requires-Python: >=3
